tests/__init__.py
tests/test_feeder.py
ticker_feeder/__init__.py
ticker_feeder/feeder.py
ticker_feeder-0.2.2.dist-info/LICENSE
ticker_feeder-0.2.2.dist-info/METADATA
ticker_feeder-0.2.2.dist-info/WHEEL
ticker_feeder-0.2.2.dist-info/top_level.txt
ticker_feeder-0.2.2.dist-info/RECORD
